{"id": "ssl", "path": "/Library/Frameworks/Python.framework/Versions/3.10/lib/python3.10/site-packages/mypy/typeshed/stdlib/ssl.pyi", "mtime": 1635356549, "size": 16955, "hash": "e7ce6198cff4ef12c193d648da7f922b77b5a3868cdc481c9abfbc3fc3983972", "data_mtime": 1635430757, "dependencies": ["socket", "sys", "_typeshed", "typing", "typing_extensions", "enum", "builtins", "abc"], "suppressed": [], "options": {"ignore_missing_imports": true, "disallow_subclassing_any": false, "implicit_reexport": true, "warn_return_any": false, "strict_optional": true, "strict_optional_whitelist": null, "disallow_incomplete_defs": false, "check_untyped_defs": false, "follow_imports": "silent", "warn_unreachable": false, "local_partial_types": false, "ignore_errors": false, "disallow_any_generics": false, "follow_imports_for_stubs": false, "strict_equality": false, "disallow_any_explicit": false, "platform": "darwin", "always_true": [], "always_false": [], "disallow_untyped_defs": false, "disallow_untyped_decorators": false, "bazel": false, "plugins": [], "disallow_untyped_calls": false, "mypyc": false, "allow_untyped_globals": false, "no_implicit_optional": false, "allow_redefinition": false, "show_none_errors": true, "warn_no_return": true, "disallow_any_unimported": false, "disallow_any_expr": false, "disallow_any_decorated": false, "warn_unused_ignores": false}, "dep_prios": [10, 10, 5, 5, 5, 10, 5, 30], "dep_lines": [1, 2, 3, 4, 5, 8, 1, 1], "interface_hash": "022b4431be03baec8614ae4dc8f1b82baad144e92bef644986c075961ded9507", "version_id": "0.910", "ignore_all": true, "plugin_data": null}