{"id": "sysconfig", "path": "/Library/Frameworks/Python.framework/Versions/3.10/lib/python3.10/site-packages/mypy/typeshed/stdlib/sysconfig.pyi", "mtime": 1635356549, "size": 871, "hash": "b3e79f7aaa59c808b259ad96bca250e8b74a2c247449a8f1f3c358e12bcba602", "data_mtime": 1635430755, "dependencies": ["typing", "builtins"], "suppressed": [], "options": {"ignore_missing_imports": true, "disallow_subclassing_any": false, "implicit_reexport": true, "warn_return_any": false, "strict_optional": true, "strict_optional_whitelist": null, "disallow_incomplete_defs": false, "check_untyped_defs": false, "follow_imports": "silent", "warn_unreachable": false, "local_partial_types": false, "ignore_errors": false, "disallow_any_generics": false, "follow_imports_for_stubs": false, "strict_equality": false, "disallow_any_explicit": false, "platform": "darwin", "always_true": [], "always_false": [], "disallow_untyped_defs": false, "disallow_untyped_decorators": false, "bazel": false, "plugins": [], "disallow_untyped_calls": false, "mypyc": false, "allow_untyped_globals": false, "no_implicit_optional": false, "allow_redefinition": false, "show_none_errors": true, "warn_no_return": true, "disallow_any_unimported": false, "disallow_any_expr": false, "disallow_any_decorated": false, "warn_unused_ignores": false}, "dep_prios": [5, 5], "dep_lines": [1, 1], "interface_hash": "a4a8502954d06a3abd5621b5743036ddde038ebe9dd1a043054a878c1b829a50", "version_id": "0.910", "ignore_all": true, "plugin_data": null}