{"id": "multiprocessing.context", "path": "/Library/Frameworks/Python.framework/Versions/3.10/lib/python3.10/site-packages/mypy/typeshed/stdlib/multiprocessing/context.pyi", "mtime": 1635356549, "size": 7475, "hash": "df3a30e7f080db7d0a9281bca954d3acd1163ad5dcc0987d289a238127eff091", "data_mtime": 1635430759, "dependencies": ["ctypes", "multiprocessing", "sys", "collections.abc", "logging", "multiprocessing.queues", "multiprocessing.synchronize", "multiprocessing.process", "multiprocessing.sharedctypes", "typing", "typing_extensions", "builtins", "abc"], "suppressed": [], "options": {"ignore_missing_imports": true, "disallow_subclassing_any": false, "implicit_reexport": true, "warn_return_any": false, "strict_optional": true, "strict_optional_whitelist": null, "disallow_incomplete_defs": false, "check_untyped_defs": false, "follow_imports": "silent", "warn_unreachable": false, "local_partial_types": false, "ignore_errors": false, "disallow_any_generics": false, "follow_imports_for_stubs": false, "strict_equality": false, "disallow_any_explicit": false, "platform": "darwin", "always_true": [], "always_false": [], "disallow_untyped_defs": false, "disallow_untyped_decorators": false, "bazel": false, "plugins": [], "disallow_untyped_calls": false, "mypyc": false, "allow_untyped_globals": false, "no_implicit_optional": false, "allow_redefinition": false, "show_none_errors": true, "warn_no_return": true, "disallow_any_unimported": false, "disallow_any_expr": false, "disallow_any_decorated": false, "warn_unused_ignores": false}, "dep_prios": [5, 10, 10, 5, 5, 10, 10, 5, 5, 5, 5, 5, 30], "dep_lines": [1, 2, 3, 4, 6, 7, 7, 8, 9, 10, 11, 1, 1], "interface_hash": "81f527f4cccaffd4e8433fe6b386cae6733282070062ba7b13bcdec73f6eb21b", "version_id": "0.910", "ignore_all": true, "plugin_data": null}